fastdoc/__init__.py
fastdoc/_nbdev.py
fastdoc/asciidoc.py
fastdoc/clean.py
fastdoc/imports.py
fastdoc-0.0.2.dist-info/LICENSE
fastdoc-0.0.2.dist-info/METADATA
fastdoc-0.0.2.dist-info/WHEEL
fastdoc-0.0.2.dist-info/entry_points.txt
fastdoc-0.0.2.dist-info/top_level.txt
fastdoc-0.0.2.dist-info/RECORD
