Metadata-Version: 2.1
Name: fastdoc
Version: 0.0.2
Summary: Convert jupyter notebooks to asciidoc
Home-page: https://github.com/fastai/fastdoc/tree/master/
Author: Sylvain Gugger and Jeremy Howard
Author-email: info@fast.ai
License: Apache Software License 2.0
Keywords: jupyter notebook asciidoc
Platform: UNKNOWN
Classifier: Development Status :: 3 - Alpha
Classifier: Intended Audience :: Developers
Classifier: License :: OSI Approved :: Apache Software License
Classifier: Natural Language :: English
Classifier: Programming Language :: Python :: 3.6
Classifier: Programming Language :: Python :: 3.7
Classifier: Programming Language :: Python :: 3.8
Requires-Python: >=3.6
Requires-Dist: jupyter-contrib-nbextensions
Requires-Dist: fastcore
Requires-Dist: nbconvert (<6)
Requires-Dist: nbdev
Requires-Dist: nbformat
Requires-Dist: pillow
